s3head/__init__.py
s3head/main.py
s3head-0.2.0.dist-info/METADATA
s3head-0.2.0.dist-info/entry_points.txt
s3head-0.2.0.dist-info/WHEEL
s3head-0.2.0.dist-info/RECORD
