Metadata-Version: 2.1
Name: s3head
Version: 0.2.0
Summary: head command for AWS S3 objects
Home-page: https://github.com/hoppiece/s3head
License: Apache-2.0
Author: Kenta Shinzato
Author-email: hoppiece@gmail.com
Requires-Python: >=3.8,<4.0
Classifier: License :: OSI Approved :: Apache Software License
Classifier: Programming Language :: Python :: 3
Classifier: Programming Language :: Python :: 3.8
Classifier: Programming Language :: Python :: 3.9
Classifier: Programming Language :: Python :: 3.10
Classifier: Programming Language :: Python :: 3.11
Requires-Dist: boto3 (>=1.26.69,<2.0.0)
Requires-Dist: click (>=8.1.3,<9.0.0)
Requires-Dist: smart-open (>=6.3.0,<7.0.0)
Project-URL: Repository, https://github.com/hoppiece/s3head
